.class public final enum Ld/g/k;
.super Ljava/lang/Enum;
.source ""


# annotations
.annotation system Ldalvik/annotation/Signature;
    value = {
        "Ljava/lang/Enum<",
        "Ld/g/k;",
        ">;"
    }
.end annotation


# static fields
.field public static final enum A:Ld/g/k;

.field public static final enum B:Ld/g/k;

.field public static final enum C:Ld/g/k;

.field public static final enum D:Ld/g/k;

.field public static final enum E:Ld/g/k;

.field public static final enum F:Ld/g/k;

.field public static final enum G:Ld/g/k;

.field public static final enum H:Ld/g/k;

.field public static final enum I:Ld/g/k;

.field public static final enum J:Ld/g/k;

.field public static final enum K:Ld/g/k;

.field public static final enum L:Ld/g/k;

.field public static final enum M:Ld/g/k;

.field public static final enum N:Ld/g/k;

.field public static final enum O:Ld/g/k;

.field public static final enum P:Ld/g/k;

.field public static final enum Q:Ld/g/k;

.field public static final enum R:Ld/g/k;

.field public static final enum S:Ld/g/k;

.field public static final enum T:Ld/g/k;

.field public static final enum U:Ld/g/k;

.field public static final enum V:Ld/g/k;

.field public static final enum W:Ld/g/k;

.field public static final enum X:Ld/g/k;

.field public static final enum Y:Ld/g/k;

.field public static final enum Z:Ld/g/k;

.field public static final enum a0:Ld/g/k;

.field public static final enum b:Ld/g/k;

.field public static final enum b0:Ld/g/k;

.field public static final enum c:Ld/g/k;

.field public static final enum c0:Ld/g/k;

.field public static final enum d:Ld/g/k;

.field public static final enum d0:Ld/g/k;

.field public static final enum e:Ld/g/k;

.field public static final enum e0:Ld/g/k;

.field public static final enum f:Ld/g/k;

.field public static final enum f0:Ld/g/k;

.field public static final enum g:Ld/g/k;

.field public static final enum g0:Ld/g/k;

.field public static final enum h:Ld/g/k;

.field public static final enum h0:Ld/g/k;

.field public static final enum i:Ld/g/k;

.field public static final enum i0:Ld/g/k;

.field public static final enum j:Ld/g/k;

.field public static final synthetic j0:[Ld/g/k;

.field public static final enum k:Ld/g/k;

.field public static final enum l:Ld/g/k;

.field public static final enum m:Ld/g/k;

.field public static final enum n:Ld/g/k;

.field public static final enum o:Ld/g/k;

.field public static final enum p:Ld/g/k;

.field public static final enum q:Ld/g/k;

.field public static final enum r:Ld/g/k;

.field public static final enum s:Ld/g/k;

.field public static final enum t:Ld/g/k;

.field public static final enum u:Ld/g/k;

.field public static final enum v:Ld/g/k;

.field public static final enum w:Ld/g/k;

.field public static final enum x:Ld/g/k;

.field public static final enum y:Ld/g/k;

.field public static final enum z:Ld/g/k;


# direct methods
.method public static constructor <clinit>()V
    .locals 16

    sget-object v0, Ld/g/l;->d:Ld/g/l;

    sget-object v1, Ld/g/l;->g:Ld/g/l;

    sget-object v2, Ld/g/l;->f:Ld/g/l;

    sget-object v3, Ld/g/l;->c:Ld/g/l;

    sget-object v4, Ld/g/l;->e:Ld/g/l;

    new-instance v5, Ld/g/k;

    const-string v6, "MOVE"

    const/4 v7, 0x0

    invoke-direct {v5, v6, v7, v3}, Ld/g/k;-><init>(Ljava/lang/String;ILd/g/l;)V

    sput-object v5, Ld/g/k;->b:Ld/g/k;

    new-instance v5, Ld/g/k;

    const-string v6, "LOADK"

    const/4 v8, 0x1

    invoke-direct {v5, v6, v8, v2}, Ld/g/k;-><init>(Ljava/lang/String;ILd/g/l;)V

    sput-object v5, Ld/g/k;->c:Ld/g/k;

    new-instance v5, Ld/g/k;

    const-string v6, "LOADBOOL"

    const/4 v9, 0x2

    invoke-direct {v5, v6, v9, v4}, Ld/g/k;-><init>(Ljava/lang/String;ILd/g/l;)V

    sput-object v5, Ld/g/k;->d:Ld/g/k;

    new-instance v5, Ld/g/k;

    const-string v6, "LOADNIL"

    const/4 v10, 0x3

    invoke-direct {v5, v6, v10, v3}, Ld/g/k;-><init>(Ljava/lang/String;ILd/g/l;)V

    sput-object v5, Ld/g/k;->e:Ld/g/k;

    new-instance v5, Ld/g/k;

    const-string v6, "GETUPVAL"

    const/4 v11, 0x4

    invoke-direct {v5, v6, v11, v3}, Ld/g/k;-><init>(Ljava/lang/String;ILd/g/l;)V

    sput-object v5, Ld/g/k;->f:Ld/g/k;

    new-instance v5, Ld/g/k;

    const-string v6, "GETGLOBAL"

    const/4 v12, 0x5

    invoke-direct {v5, v6, v12, v2}, Ld/g/k;-><init>(Ljava/lang/String;ILd/g/l;)V

    sput-object v5, Ld/g/k;->g:Ld/g/k;

    new-instance v5, Ld/g/k;

    const-string v6, "GETTABLE"

    const/4 v13, 0x6

    invoke-direct {v5, v6, v13, v4}, Ld/g/k;-><init>(Ljava/lang/String;ILd/g/l;)V

    sput-object v5, Ld/g/k;->h:Ld/g/k;

    new-instance v5, Ld/g/k;

    const-string v6, "SETGLOBAL"

    const/4 v14, 0x7

    invoke-direct {v5, v6, v14, v2}, Ld/g/k;-><init>(Ljava/lang/String;ILd/g/l;)V

    sput-object v5, Ld/g/k;->i:Ld/g/k;

    new-instance v5, Ld/g/k;

    const-string v6, "SETUPVAL"

    const/16 v15, 0x8

    invoke-direct {v5, v6, v15, v3}, Ld/g/k;-><init>(Ljava/lang/String;ILd/g/l;)V

    sput-object v5, Ld/g/k;->j:Ld/g/k;

    new-instance v5, Ld/g/k;

    const-string v6, "SETTABLE"

    const/16 v15, 0x9

    invoke-direct {v5, v6, v15, v4}, Ld/g/k;-><init>(Ljava/lang/String;ILd/g/l;)V

    sput-object v5, Ld/g/k;->k:Ld/g/k;

    new-instance v5, Ld/g/k;

    const-string v6, "NEWTABLE"

    const/16 v15, 0xa

    invoke-direct {v5, v6, v15, v4}, Ld/g/k;-><init>(Ljava/lang/String;ILd/g/l;)V

    sput-object v5, Ld/g/k;->l:Ld/g/k;

    new-instance v5, Ld/g/k;

    const-string v6, "SELF"

    const/16 v15, 0xb

    invoke-direct {v5, v6, v15, v4}, Ld/g/k;-><init>(Ljava/lang/String;ILd/g/l;)V

    sput-object v5, Ld/g/k;->m:Ld/g/k;

    new-instance v5, Ld/g/k;

    const-string v6, "ADD"

    const/16 v15, 0xc

    invoke-direct {v5, v6, v15, v4}, Ld/g/k;-><init>(Ljava/lang/String;ILd/g/l;)V

    sput-object v5, Ld/g/k;->n:Ld/g/k;

    new-instance v5, Ld/g/k;

    const-string v6, "SUB"

    const/16 v15, 0xd

    invoke-direct {v5, v6, v15, v4}, Ld/g/k;-><init>(Ljava/lang/String;ILd/g/l;)V

    sput-object v5, Ld/g/k;->o:Ld/g/k;

    new-instance v5, Ld/g/k;

    const-string v6, "MUL"

    const/16 v15, 0xe

    invoke-direct {v5, v6, v15, v4}, Ld/g/k;-><init>(Ljava/lang/String;ILd/g/l;)V

    sput-object v5, Ld/g/k;->p:Ld/g/k;

    new-instance v5, Ld/g/k;

    const-string v6, "DIV"

    const/16 v15, 0xf

    invoke-direct {v5, v6, v15, v4}, Ld/g/k;-><init>(Ljava/lang/String;ILd/g/l;)V

    sput-object v5, Ld/g/k;->q:Ld/g/k;

    new-instance v5, Ld/g/k;

    const-string v6, "MOD"

    const/16 v15, 0x10

    invoke-direct {v5, v6, v15, v4}, Ld/g/k;-><init>(Ljava/lang/String;ILd/g/l;)V

    sput-object v5, Ld/g/k;->r:Ld/g/k;

    new-instance v5, Ld/g/k;

    const-string v6, "POW"

    const/16 v15, 0x11

    invoke-direct {v5, v6, v15, v4}, Ld/g/k;-><init>(Ljava/lang/String;ILd/g/l;)V

    sput-object v5, Ld/g/k;->s:Ld/g/k;

    new-instance v5, Ld/g/k;

    const-string v6, "UNM"

    const/16 v15, 0x12

    invoke-direct {v5, v6, v15, v3}, Ld/g/k;-><init>(Ljava/lang/String;ILd/g/l;)V

    sput-object v5, Ld/g/k;->t:Ld/g/k;

    new-instance v5, Ld/g/k;

    const-string v6, "NOT"

    const/16 v15, 0x13

    invoke-direct {v5, v6, v15, v3}, Ld/g/k;-><init>(Ljava/lang/String;ILd/g/l;)V

    sput-object v5, Ld/g/k;->u:Ld/g/k;

    new-instance v5, Ld/g/k;

    const-string v6, "LEN"

    const/16 v15, 0x14

    invoke-direct {v5, v6, v15, v3}, Ld/g/k;-><init>(Ljava/lang/String;ILd/g/l;)V

    sput-object v5, Ld/g/k;->v:Ld/g/k;

    new-instance v5, Ld/g/k;

    const-string v6, "CONCAT"

    const/16 v15, 0x15

    invoke-direct {v5, v6, v15, v4}, Ld/g/k;-><init>(Ljava/lang/String;ILd/g/l;)V

    sput-object v5, Ld/g/k;->w:Ld/g/k;

    new-instance v5, Ld/g/k;

    sget-object v6, Ld/g/l;->i:Ld/g/l;

    const-string v15, "JMP"

    const/16 v14, 0x16

    invoke-direct {v5, v15, v14, v6}, Ld/g/k;-><init>(Ljava/lang/String;ILd/g/l;)V

    sput-object v5, Ld/g/k;->x:Ld/g/k;

    new-instance v5, Ld/g/k;

    const-string v6, "EQ"

    const/16 v14, 0x17

    invoke-direct {v5, v6, v14, v4}, Ld/g/k;-><init>(Ljava/lang/String;ILd/g/l;)V

    sput-object v5, Ld/g/k;->y:Ld/g/k;

    new-instance v5, Ld/g/k;

    const-string v6, "LT"

    const/16 v14, 0x18

    invoke-direct {v5, v6, v14, v4}, Ld/g/k;-><init>(Ljava/lang/String;ILd/g/l;)V

    sput-object v5, Ld/g/k;->z:Ld/g/k;

    new-instance v5, Ld/g/k;

    const-string v6, "LE"

    const/16 v14, 0x19

    invoke-direct {v5, v6, v14, v4}, Ld/g/k;-><init>(Ljava/lang/String;ILd/g/l;)V

    sput-object v5, Ld/g/k;->A:Ld/g/k;

    new-instance v5, Ld/g/k;

    const-string v6, "TEST"

    const/16 v14, 0x1a

    invoke-direct {v5, v6, v14, v0}, Ld/g/k;-><init>(Ljava/lang/String;ILd/g/l;)V

    sput-object v5, Ld/g/k;->B:Ld/g/k;

    new-instance v5, Ld/g/k;

    const-string v6, "TESTSET"

    const/16 v14, 0x1b

    invoke-direct {v5, v6, v14, v4}, Ld/g/k;-><init>(Ljava/lang/String;ILd/g/l;)V

    sput-object v5, Ld/g/k;->C:Ld/g/k;

    new-instance v5, Ld/g/k;

    const-string v6, "CALL"

    const/16 v14, 0x1c

    invoke-direct {v5, v6, v14, v4}, Ld/g/k;-><init>(Ljava/lang/String;ILd/g/l;)V

    sput-object v5, Ld/g/k;->D:Ld/g/k;

    new-instance v5, Ld/g/k;

    const-string v6, "TAILCALL"

    const/16 v14, 0x1d

    invoke-direct {v5, v6, v14, v4}, Ld/g/k;-><init>(Ljava/lang/String;ILd/g/l;)V

    sput-object v5, Ld/g/k;->E:Ld/g/k;

    new-instance v5, Ld/g/k;

    const-string v6, "RETURN"

    const/16 v14, 0x1e

    invoke-direct {v5, v6, v14, v3}, Ld/g/k;-><init>(Ljava/lang/String;ILd/g/l;)V

    sput-object v5, Ld/g/k;->F:Ld/g/k;

    new-instance v5, Ld/g/k;

    const-string v6, "FORLOOP"

    const/16 v14, 0x1f

    invoke-direct {v5, v6, v14, v1}, Ld/g/k;-><init>(Ljava/lang/String;ILd/g/l;)V

    sput-object v5, Ld/g/k;->G:Ld/g/k;

    new-instance v5, Ld/g/k;

    const-string v6, "FORPREP"

    const/16 v14, 0x20

    invoke-direct {v5, v6, v14, v1}, Ld/g/k;-><init>(Ljava/lang/String;ILd/g/l;)V

    sput-object v5, Ld/g/k;->H:Ld/g/k;

    new-instance v5, Ld/g/k;

    const-string v6, "TFORLOOP"

    const/16 v14, 0x21

    invoke-direct {v5, v6, v14, v0}, Ld/g/k;-><init>(Ljava/lang/String;ILd/g/l;)V

    sput-object v5, Ld/g/k;->I:Ld/g/k;

    new-instance v5, Ld/g/k;

    const-string v6, "SETLIST"

    const/16 v14, 0x22

    invoke-direct {v5, v6, v14, v4}, Ld/g/k;-><init>(Ljava/lang/String;ILd/g/l;)V

    sput-object v5, Ld/g/k;->J:Ld/g/k;

    new-instance v5, Ld/g/k;

    sget-object v6, Ld/g/l;->b:Ld/g/l;

    const-string v14, "CLOSE"

    const/16 v15, 0x23

    invoke-direct {v5, v14, v15, v6}, Ld/g/k;-><init>(Ljava/lang/String;ILd/g/l;)V

    sput-object v5, Ld/g/k;->K:Ld/g/k;

    new-instance v5, Ld/g/k;

    const-string v6, "CLOSURE"

    const/16 v14, 0x24

    invoke-direct {v5, v6, v14, v2}, Ld/g/k;-><init>(Ljava/lang/String;ILd/g/l;)V

    sput-object v5, Ld/g/k;->L:Ld/g/k;

    new-instance v5, Ld/g/k;

    const-string v6, "VARARG"

    const/16 v14, 0x25

    invoke-direct {v5, v6, v14, v3}, Ld/g/k;-><init>(Ljava/lang/String;ILd/g/l;)V

    sput-object v5, Ld/g/k;->M:Ld/g/k;

    new-instance v5, Ld/g/k;

    const-string v6, "JMP52"

    const/16 v14, 0x26

    invoke-direct {v5, v6, v14, v1}, Ld/g/k;-><init>(Ljava/lang/String;ILd/g/l;)V

    sput-object v5, Ld/g/k;->N:Ld/g/k;

    new-instance v5, Ld/g/k;

    const-string v6, "LOADNIL52"

    const/16 v14, 0x27

    invoke-direct {v5, v6, v14, v3}, Ld/g/k;-><init>(Ljava/lang/String;ILd/g/l;)V

    sput-object v5, Ld/g/k;->O:Ld/g/k;

    new-instance v5, Ld/g/k;

    sget-object v6, Ld/g/l;->b:Ld/g/l;

    const-string v14, "LOADKX"

    const/16 v15, 0x28

    invoke-direct {v5, v14, v15, v6}, Ld/g/k;-><init>(Ljava/lang/String;ILd/g/l;)V

    sput-object v5, Ld/g/k;->P:Ld/g/k;

    new-instance v5, Ld/g/k;

    const-string v6, "GETTABUP"

    const/16 v14, 0x29

    invoke-direct {v5, v6, v14, v4}, Ld/g/k;-><init>(Ljava/lang/String;ILd/g/l;)V

    sput-object v5, Ld/g/k;->Q:Ld/g/k;

    new-instance v5, Ld/g/k;

    const-string v6, "SETTABUP"

    const/16 v14, 0x2a

    invoke-direct {v5, v6, v14, v4}, Ld/g/k;-><init>(Ljava/lang/String;ILd/g/l;)V

    sput-object v5, Ld/g/k;->R:Ld/g/k;

    new-instance v5, Ld/g/k;

    const-string v6, "SETLIST52"

    const/16 v14, 0x2b

    invoke-direct {v5, v6, v14, v4}, Ld/g/k;-><init>(Ljava/lang/String;ILd/g/l;)V

    sput-object v5, Ld/g/k;->S:Ld/g/k;

    new-instance v5, Ld/g/k;

    const-string v6, "TFORCALL"

    const/16 v14, 0x2c

    invoke-direct {v5, v6, v14, v0}, Ld/g/k;-><init>(Ljava/lang/String;ILd/g/l;)V

    sput-object v5, Ld/g/k;->T:Ld/g/k;

    new-instance v0, Ld/g/k;

    sget-object v5, Ld/g/l;->h:Ld/g/l;

    const-string v6, "EXTRAARG"

    const/16 v14, 0x2d

    invoke-direct {v0, v6, v14, v5}, Ld/g/k;-><init>(Ljava/lang/String;ILd/g/l;)V

    sput-object v0, Ld/g/k;->U:Ld/g/k;

    new-instance v0, Ld/g/k;

    const-string v5, "NEWTABLE50"

    const/16 v6, 0x2e

    invoke-direct {v0, v5, v6, v4}, Ld/g/k;-><init>(Ljava/lang/String;ILd/g/l;)V

    sput-object v0, Ld/g/k;->V:Ld/g/k;

    new-instance v0, Ld/g/k;

    const-string v5, "SETLIST50"

    const/16 v6, 0x2f

    invoke-direct {v0, v5, v6, v4}, Ld/g/k;-><init>(Ljava/lang/String;ILd/g/l;)V

    sput-object v0, Ld/g/k;->W:Ld/g/k;

    new-instance v0, Ld/g/k;

    const-string v5, "SETLISTO"

    const/16 v6, 0x30

    invoke-direct {v0, v5, v6, v2}, Ld/g/k;-><init>(Ljava/lang/String;ILd/g/l;)V

    sput-object v0, Ld/g/k;->X:Ld/g/k;

    new-instance v0, Ld/g/k;

    const-string v2, "TFORPREP"

    const/16 v5, 0x31

    invoke-direct {v0, v2, v5, v1}, Ld/g/k;-><init>(Ljava/lang/String;ILd/g/l;)V

    sput-object v0, Ld/g/k;->Y:Ld/g/k;

    new-instance v0, Ld/g/k;

    const-string v1, "TEST50"

    const/16 v2, 0x32

    invoke-direct {v0, v1, v2, v4}, Ld/g/k;-><init>(Ljava/lang/String;ILd/g/l;)V

    sput-object v0, Ld/g/k;->Z:Ld/g/k;

    new-instance v0, Ld/g/k;

    const-string v1, "IDIV"

    const/16 v2, 0x33

    invoke-direct {v0, v1, v2, v4}, Ld/g/k;-><init>(Ljava/lang/String;ILd/g/l;)V

    sput-object v0, Ld/g/k;->a0:Ld/g/k;

    new-instance v0, Ld/g/k;

    const-string v1, "BAND"

    const/16 v2, 0x34

    invoke-direct {v0, v1, v2, v4}, Ld/g/k;-><init>(Ljava/lang/String;ILd/g/l;)V

    sput-object v0, Ld/g/k;->b0:Ld/g/k;

    new-instance v0, Ld/g/k;

    const-string v1, "BOR"

    const/16 v2, 0x35

    invoke-direct {v0, v1, v2, v4}, Ld/g/k;-><init>(Ljava/lang/String;ILd/g/l;)V

    sput-object v0, Ld/g/k;->c0:Ld/g/k;

    new-instance v0, Ld/g/k;

    const-string v1, "BXOR"

    const/16 v2, 0x36

    invoke-direct {v0, v1, v2, v4}, Ld/g/k;-><init>(Ljava/lang/String;ILd/g/l;)V

    sput-object v0, Ld/g/k;->d0:Ld/g/k;

    new-instance v0, Ld/g/k;

    const-string v1, "SHL"

    const/16 v2, 0x37

    invoke-direct {v0, v1, v2, v4}, Ld/g/k;-><init>(Ljava/lang/String;ILd/g/l;)V

    sput-object v0, Ld/g/k;->e0:Ld/g/k;

    new-instance v0, Ld/g/k;

    const-string v1, "SHR"

    const/16 v2, 0x38

    invoke-direct {v0, v1, v2, v4}, Ld/g/k;-><init>(Ljava/lang/String;ILd/g/l;)V

    sput-object v0, Ld/g/k;->f0:Ld/g/k;

    new-instance v0, Ld/g/k;

    const-string v1, "BNOT"

    const/16 v2, 0x39

    invoke-direct {v0, v1, v2, v3}, Ld/g/k;-><init>(Ljava/lang/String;ILd/g/l;)V

    sput-object v0, Ld/g/k;->g0:Ld/g/k;

    new-instance v0, Ld/g/k;

    const-string v1, "UNKNOW"

    const/16 v2, 0x3a

    invoke-direct {v0, v1, v2, v3}, Ld/g/k;-><init>(Ljava/lang/String;ILd/g/l;)V

    sput-object v0, Ld/g/k;->h0:Ld/g/k;

    new-instance v0, Ld/g/k;

    sget-object v1, Ld/g/l;->j:Ld/g/l;

    const-string v2, "EXTRABYTE"

    const/16 v3, 0x3b

    invoke-direct {v0, v2, v3, v1}, Ld/g/k;-><init>(Ljava/lang/String;ILd/g/l;)V

    sput-object v0, Ld/g/k;->i0:Ld/g/k;

    const/16 v1, 0x3c

    new-array v1, v1, [Ld/g/k;

    sget-object v2, Ld/g/k;->b:Ld/g/k;

    aput-object v2, v1, v7

    sget-object v2, Ld/g/k;->c:Ld/g/k;

    aput-object v2, v1, v8

    sget-object v2, Ld/g/k;->d:Ld/g/k;

    aput-object v2, v1, v9

    sget-object v2, Ld/g/k;->e:Ld/g/k;

    aput-object v2, v1, v10

    sget-object v2, Ld/g/k;->f:Ld/g/k;

    aput-object v2, v1, v11

    sget-object v2, Ld/g/k;->g:Ld/g/k;

    aput-object v2, v1, v12

    sget-object v2, Ld/g/k;->h:Ld/g/k;

    aput-object v2, v1, v13

    sget-object v2, Ld/g/k;->i:Ld/g/k;

    const/4 v3, 0x7

    aput-object v2, v1, v3

    sget-object v2, Ld/g/k;->j:Ld/g/k;

    const/16 v3, 0x8

    aput-object v2, v1, v3

    sget-object v2, Ld/g/k;->k:Ld/g/k;

    const/16 v3, 0x9

    aput-object v2, v1, v3

    sget-object v2, Ld/g/k;->l:Ld/g/k;

    const/16 v3, 0xa

    aput-object v2, v1, v3

    sget-object v2, Ld/g/k;->m:Ld/g/k;

    const/16 v3, 0xb

    aput-object v2, v1, v3

    sget-object v2, Ld/g/k;->n:Ld/g/k;

    const/16 v3, 0xc

    aput-object v2, v1, v3

    sget-object v2, Ld/g/k;->o:Ld/g/k;

    const/16 v3, 0xd

    aput-object v2, v1, v3

    sget-object v2, Ld/g/k;->p:Ld/g/k;

    const/16 v3, 0xe

    aput-object v2, v1, v3

    sget-object v2, Ld/g/k;->q:Ld/g/k;

    const/16 v3, 0xf

    aput-object v2, v1, v3

    sget-object v2, Ld/g/k;->r:Ld/g/k;

    const/16 v3, 0x10

    aput-object v2, v1, v3

    sget-object v2, Ld/g/k;->s:Ld/g/k;

    const/16 v3, 0x11

    aput-object v2, v1, v3

    sget-object v2, Ld/g/k;->t:Ld/g/k;

    const/16 v3, 0x12

    aput-object v2, v1, v3

    sget-object v2, Ld/g/k;->u:Ld/g/k;

    const/16 v3, 0x13

    aput-object v2, v1, v3

    sget-object v2, Ld/g/k;->v:Ld/g/k;

    const/16 v3, 0x14

    aput-object v2, v1, v3

    sget-object v2, Ld/g/k;->w:Ld/g/k;

    const/16 v3, 0x15

    aput-object v2, v1, v3

    sget-object v2, Ld/g/k;->x:Ld/g/k;

    const/16 v3, 0x16

    aput-object v2, v1, v3

    sget-object v2, Ld/g/k;->y:Ld/g/k;

    const/16 v3, 0x17

    aput-object v2, v1, v3

    sget-object v2, Ld/g/k;->z:Ld/g/k;

    const/16 v3, 0x18

    aput-object v2, v1, v3

    sget-object v2, Ld/g/k;->A:Ld/g/k;

    const/16 v3, 0x19

    aput-object v2, v1, v3

    sget-object v2, Ld/g/k;->B:Ld/g/k;

    const/16 v3, 0x1a

    aput-object v2, v1, v3

    sget-object v2, Ld/g/k;->C:Ld/g/k;

    const/16 v3, 0x1b

    aput-object v2, v1, v3

    sget-object v2, Ld/g/k;->D:Ld/g/k;

    const/16 v3, 0x1c

    aput-object v2, v1, v3

    sget-object v2, Ld/g/k;->E:Ld/g/k;

    const/16 v3, 0x1d

    aput-object v2, v1, v3

    sget-object v2, Ld/g/k;->F:Ld/g/k;

    const/16 v3, 0x1e

    aput-object v2, v1, v3

    sget-object v2, Ld/g/k;->G:Ld/g/k;

    const/16 v3, 0x1f

    aput-object v2, v1, v3

    sget-object v2, Ld/g/k;->H:Ld/g/k;

    const/16 v3, 0x20

    aput-object v2, v1, v3

    sget-object v2, Ld/g/k;->I:Ld/g/k;

    const/16 v3, 0x21

    aput-object v2, v1, v3

    sget-object v2, Ld/g/k;->J:Ld/g/k;

    const/16 v3, 0x22

    aput-object v2, v1, v3

    sget-object v2, Ld/g/k;->K:Ld/g/k;

    const/16 v3, 0x23

    aput-object v2, v1, v3

    sget-object v2, Ld/g/k;->L:Ld/g/k;

    const/16 v3, 0x24

    aput-object v2, v1, v3

    sget-object v2, Ld/g/k;->M:Ld/g/k;

    const/16 v3, 0x25

    aput-object v2, v1, v3

    sget-object v2, Ld/g/k;->N:Ld/g/k;

    const/16 v3, 0x26

    aput-object v2, v1, v3

    sget-object v2, Ld/g/k;->O:Ld/g/k;

    const/16 v3, 0x27

    aput-object v2, v1, v3

    sget-object v2, Ld/g/k;->P:Ld/g/k;

    const/16 v3, 0x28

    aput-object v2, v1, v3

    sget-object v2, Ld/g/k;->Q:Ld/g/k;

    const/16 v3, 0x29

    aput-object v2, v1, v3

    sget-object v2, Ld/g/k;->R:Ld/g/k;

    const/16 v3, 0x2a

    aput-object v2, v1, v3

    sget-object v2, Ld/g/k;->S:Ld/g/k;

    const/16 v3, 0x2b

    aput-object v2, v1, v3

    sget-object v2, Ld/g/k;->T:Ld/g/k;

    const/16 v3, 0x2c

    aput-object v2, v1, v3

    sget-object v2, Ld/g/k;->U:Ld/g/k;

    const/16 v3, 0x2d

    aput-object v2, v1, v3

    sget-object v2, Ld/g/k;->V:Ld/g/k;

    const/16 v3, 0x2e

    aput-object v2, v1, v3

    sget-object v2, Ld/g/k;->W:Ld/g/k;

    const/16 v3, 0x2f

    aput-object v2, v1, v3

    sget-object v2, Ld/g/k;->X:Ld/g/k;

    const/16 v3, 0x30

    aput-object v2, v1, v3

    sget-object v2, Ld/g/k;->Y:Ld/g/k;

    const/16 v3, 0x31

    aput-object v2, v1, v3

    sget-object v2, Ld/g/k;->Z:Ld/g/k;

    const/16 v3, 0x32

    aput-object v2, v1, v3

    sget-object v2, Ld/g/k;->a0:Ld/g/k;

    const/16 v3, 0x33

    aput-object v2, v1, v3

    sget-object v2, Ld/g/k;->b0:Ld/g/k;

    const/16 v3, 0x34

    aput-object v2, v1, v3

    sget-object v2, Ld/g/k;->c0:Ld/g/k;

    const/16 v3, 0x35

    aput-object v2, v1, v3

    sget-object v2, Ld/g/k;->d0:Ld/g/k;

    const/16 v3, 0x36

    aput-object v2, v1, v3

    sget-object v2, Ld/g/k;->e0:Ld/g/k;

    const/16 v3, 0x37

    aput-object v2, v1, v3

    sget-object v2, Ld/g/k;->f0:Ld/g/k;

    const/16 v3, 0x38

    aput-object v2, v1, v3

    sget-object v2, Ld/g/k;->g0:Ld/g/k;

    const/16 v3, 0x39

    aput-object v2, v1, v3

    sget-object v2, Ld/g/k;->h0:Ld/g/k;

    const/16 v3, 0x3a

    aput-object v2, v1, v3

    const/16 v2, 0x3b

    aput-object v0, v1, v2

    sput-object v1, Ld/g/k;->j0:[Ld/g/k;

    return-void
.end method

.method public constructor <init>(Ljava/lang/String;ILd/g/l;)V
    .locals 0
    .annotation system Ldalvik/annotation/Signature;
        value = {
            "(",
            "Ld/g/l;",
            ")V"
        }
    .end annotation

    invoke-direct {p0, p1, p2}, Ljava/lang/Enum;-><init>(Ljava/lang/String;I)V

    return-void
.end method

.method public static valueOf(Ljava/lang/String;)Ld/g/k;
    .locals 1

    const-class v0, Ld/g/k;

    invoke-static {v0, p0}, Ljava/lang/Enum;->valueOf(Ljava/lang/Class;Ljava/lang/String;)Ljava/lang/Enum;

    move-result-object p0

    check-cast p0, Ld/g/k;

    return-object p0
.end method

.method public static values()[Ld/g/k;
    .locals 1

    sget-object v0, Ld/g/k;->j0:[Ld/g/k;

    invoke-virtual {v0}, [Ld/g/k;->clone()Ljava/lang/Object;

    move-result-object v0

    check-cast v0, [Ld/g/k;

    return-object v0
.end method


# virtual methods
.method public a(ILd/g/c;)I
    .locals 3

    invoke-virtual {p0}, Ljava/lang/Enum;->ordinal()I

    move-result v0

    const/4 v1, 0x2

    const/4 v2, -0x1

    packed-switch v0, :pswitch_data_0

    new-instance p1, Ljava/lang/IllegalStateException;

    invoke-direct {p1}, Ljava/lang/IllegalStateException;-><init>()V

    throw p1

    :pswitch_0
    return v2

    :pswitch_1
    invoke-interface {p2, p1}, Ld/g/c;->e(I)I

    move-result v0

    invoke-interface {p2, p1}, Ld/g/c;->c(I)I

    move-result p1

    if-eq p1, v1, :cond_0

    return v2

    :cond_0
    return v0

    :pswitch_2
    invoke-interface {p2, p1}, Ld/g/c;->e(I)I

    move-result v0

    invoke-interface {p2, p1}, Ld/g/c;->c(I)I

    move-result p1

    if-ne p1, v1, :cond_1

    return v0

    :cond_1
    return v2

    :pswitch_3
    invoke-interface {p2, p1}, Ld/g/c;->e(I)I

    move-result v0

    invoke-interface {p2, p1}, Ld/g/c;->d(I)I

    move-result p1

    if-ne p1, v1, :cond_2

    return v0

    :cond_2
    :pswitch_4
    return v2

    :pswitch_5
    invoke-interface {p2, p1}, Ld/g/c;->c(I)I

    move-result v0

    if-nez v0, :cond_3

    invoke-interface {p2, p1}, Ld/g/c;->e(I)I

    move-result p1

    return p1

    :cond_3
    return v2

    :pswitch_6
    invoke-interface {p2, p1}, Ld/g/c;->e(I)I

    move-result v0

    invoke-interface {p2, p1}, Ld/g/c;->c(I)I

    move-result v1

    if-ne v0, v1, :cond_4

    invoke-interface {p2, p1}, Ld/g/c;->e(I)I

    move-result p1

    return p1

    :cond_4
    return v2

    :pswitch_7
    invoke-interface {p2, p1}, Ld/g/c;->e(I)I

    move-result p1

    return p1

    nop

    :pswitch_data_0
    .packed-switch 0x0
        :pswitch_7
        :pswitch_7
        :pswitch_7
        :pswitch_6
        :pswitch_7
        :pswitch_7
        :pswitch_7
        :pswitch_4
        :pswitch_4
        :pswitch_4
        :pswitch_7
        :pswitch_4
        :pswitch_7
        :pswitch_7
        :pswitch_7
        :pswitch_7
        :pswitch_7
        :pswitch_7
        :pswitch_7
        :pswitch_7
        :pswitch_7
        :pswitch_7
        :pswitch_4
        :pswitch_4
        :pswitch_4
        :pswitch_4
        :pswitch_4
        :pswitch_7
        :pswitch_3
        :pswitch_4
        :pswitch_4
        :pswitch_4
        :pswitch_4
        :pswitch_4
        :pswitch_4
        :pswitch_4
        :pswitch_7
        :pswitch_2
        :pswitch_4
        :pswitch_5
        :pswitch_7
        :pswitch_7
        :pswitch_4
        :pswitch_4
        :pswitch_4
        :pswitch_4
        :pswitch_7
        :pswitch_4
        :pswitch_4
        :pswitch_4
        :pswitch_7
        :pswitch_7
        :pswitch_7
        :pswitch_7
        :pswitch_7
        :pswitch_7
        :pswitch_7
        :pswitch_7
        :pswitch_1
        :pswitch_0
    .end packed-switch
.end method
